{"_type":"export","__export_format":4,"__export_date":"2020-06-08T15:28:38.112Z","__export_source":"insomnia.desktop.app:v7.1.1","resources":[{"_id":"req_4556ac93c6d447959a0c940ed0f0b5a1","authentication":{},"body":{"mimeType":"application/json","text":"{\n\t\"person_name\": \"Lucas Vieira\",\n\t\"person_cpf\": \"15651\",\n\t\"card_number\": \"155616\",\n\t\"card_cvv\":\"94\",\n\t\"card_exp\":\"siodjfs\",\n\t\"card_limit\": \"500\",\n\t\"card_saldo\":\"100000\",\n\t\"card_fat\":\"fiodsj\"\n}"},"created":1591628958291,"description":"","headers":[{"id":"pair_b1e6bf2787e74a61b9b96c22f2f7797e","name":"Content-Type","value":"application/json"}],"isPrivate":false,"metaSortKey":-1591628958291,"method":"POST","modified":1591629656438,"name":"Create","parameters":[],"parentId":"fld_8b94b05a03e9487d855264d886caed3a","settingDisableRenderRequestBody":false,"settingEncodeUrl":true,"settingFollowRedirects":"global","settingRebuildPath":true,"settingSendCookies":true,"settingStoreCookies":true,"url":"{{ base_URL  }}/create_client","_type":"request"},{"_id":"fld_8b94b05a03e9487d855264d886caed3a","created":1591628930450,"description":"","environment":{},"environmentPropertyOrder":null,"metaSortKey":-1591628936317,"modified":1591628940088,"name":"POST","parentId":"wrk_203fd2742f574ba3b18054d158f5d06f","_type":"request_group"},{"_id":"wrk_203fd2742f574ba3b18054d158f5d06f","created":1591628891861,"description":"","modified":1591628891861,"name":"API - Open Banking","parentId":null,"_type":"workspace"},{"_id":"req_e8139abcd3b444df96d16dd55a8004ca","authentication":{},"body":{},"created":1591628997930,"description":"","headers":[],"isPrivate":false,"metaSortKey":-1591628998005,"method":"GET","modified":1591629049444,"name":"Index ( All Clients )","parameters":[],"parentId":"fld_d9aa8e40519a463885c925c47ef90a01","settingDisableRenderRequestBody":false,"settingEncodeUrl":true,"settingFollowRedirects":"global","settingRebuildPath":true,"settingSendCookies":true,"settingStoreCookies":true,"url":"{{ base_URL  }}/clients","_type":"request"},{"_id":"fld_d9aa8e40519a463885c925c47ef90a01","created":1591628926244,"description":"","environment":{},"environmentPropertyOrder":null,"metaSortKey":-1591628936292,"modified":1591628941855,"name":"GET","parentId":"wrk_203fd2742f574ba3b18054d158f5d06f","_type":"request_group"},{"_id":"req_87f0893ec64b43269eb1da62e00742df","authentication":{},"body":{},"created":1591629043193,"description":"","headers":[],"isPrivate":false,"metaSortKey":-1591628997955,"method":"GET","modified":1591629062270,"name":"Show ( One Client )","parameters":[],"parentId":"fld_d9aa8e40519a463885c925c47ef90a01","settingDisableRenderRequestBody":false,"settingEncodeUrl":true,"settingFollowRedirects":"global","settingRebuildPath":true,"settingSendCookies":true,"settingStoreCookies":true,"url":"{{ base_URL  }}/client/5ecd7c14acbf0793f571ecc","_type":"request"},{"_id":"req_18cdfab1d05a4a8d865ca557076844f1","authentication":{},"body":{},"created":1591629121648,"description":"","headers":[],"isPrivate":false,"metaSortKey":-1591628997905,"method":"GET","modified":1591629134236,"name":"Limite do Cliente","parameters":[],"parentId":"fld_d9aa8e40519a463885c925c47ef90a01","settingDisableRenderRequestBody":false,"settingEncodeUrl":true,"settingFollowRedirects":"global","settingRebuildPath":true,"settingSendCookies":true,"settingStoreCookies":true,"url":"{{ base_URL  }}/client_limit/5ecd7c14acbf0793fa571ecc","_type":"request"},{"_id":"req_b45e4d5f9b7f49c284f0575b399d242d","authentication":{},"body":{},"created":1591629151291,"description":"","headers":[],"isPrivate":false,"metaSortKey":-1591628997855,"method":"GET","modified":1591629171343,"name":"Fatura do Cliente","parameters":[],"parentId":"fld_d9aa8e40519a463885c925c47ef90a01","settingDisableRenderRequestBody":false,"settingEncodeUrl":true,"settingFollowRedirects":"global","settingRebuildPath":true,"settingSendCookies":true,"settingStoreCookies":true,"url":"{{ base_URL  }}/client_fatura/5ecd7c14acbf0793fa571ecc","_type":"request"},{"_id":"req_aad2d005d9e44e758d2e42fc4b8a7649","authentication":{},"body":{},"created":1591629169050,"description":"","headers":[],"isPrivate":false,"metaSortKey":-1591628997805,"method":"GET","modified":1591629180573,"name":"Saldo do Cliente","parameters":[],"parentId":"fld_d9aa8e40519a463885c925c47ef90a01","settingDisableRenderRequestBody":false,"settingEncodeUrl":true,"settingFollowRedirects":"global","settingRebuildPath":true,"settingSendCookies":true,"settingStoreCookies":true,"url":"{{ base_URL  }}/client_saldo/5ecd7c14acbf0793fa571ecc","_type":"request"},{"_id":"req_1a1409146d184729a64ef136a03dc670","authentication":{},"body":{"mimeType":"application/json","text":"{\n  \"person_name\": \"João Tomé\",\n  \"person_cpf\": \"223344556677\",\n  \"card_number\": \"87654321\",\n  \"card_cvv\": \"321\",\n  \"card_exp\": \"31/12\",\n  \"card_limit\": \"88888\",\n  \"card_saldo\": \"2000000\",\n\t\"card_fat\": null\n}"},"created":1591629232620,"description":"","headers":[{"id":"pair_71eef358ed91481bbee2d78179498d7c","name":"Content-Type","value":"application/json"}],"isPrivate":false,"metaSortKey":-1591629232620,"method":"PUT","modified":1591629725222,"name":"Atualizar Cliente ( GERAL )","parameters":[],"parentId":"fld_ebbc21a3c78a4a29a3341034bd9d18a5","settingDisableRenderRequestBody":false,"settingEncodeUrl":true,"settingFollowRedirects":"global","settingRebuildPath":true,"settingSendCookies":true,"settingStoreCookies":true,"url":"{{ base_URL  }}/update_client/5ede569c0c36605787a9714f","_type":"request"},{"_id":"fld_ebbc21a3c78a4a29a3341034bd9d18a5","created":1591628932987,"description":"","environment":{},"environmentPropertyOrder":null,"metaSortKey":-1591628932987,"modified":1591628932987,"name":"PUT","parentId":"wrk_203fd2742f574ba3b18054d158f5d06f","_type":"request_group"},{"_id":"req_fb84c7b36d4f46de9a1bf296fb754346","authentication":{},"body":{},"created":1591629267964,"description":"","headers":[],"isPrivate":false,"metaSortKey":-1591629267964,"method":"DELETE","modified":1591629277778,"name":"Deletar Cliente","parameters":[],"parentId":"fld_08f0d9285a2740659d199c8338d1a59b","settingDisableRenderRequestBody":false,"settingEncodeUrl":true,"settingFollowRedirects":"global","settingRebuildPath":true,"settingSendCookies":true,"settingStoreCookies":true,"url":"{{ base_URL  }}/delete_client/5ecd7c14acbf0793fa571ecc","_type":"request"},{"_id":"fld_08f0d9285a2740659d199c8338d1a59b","created":1591628936267,"description":"","environment":{},"environmentPropertyOrder":null,"metaSortKey":-1591628932937,"modified":1591628943424,"name":"DELETE","parentId":"wrk_203fd2742f574ba3b18054d158f5d06f","_type":"request_group"},{"_id":"env_95be4cb6dfbce88b8b250b7576671f1b8111e4be","color":null,"created":1591628891975,"data":{"base_URL":"http://localhost:8080"},"dataPropertyOrder":{"&":["base_URL"]},"isPrivate":false,"metaSortKey":1591628891975,"modified":1591628914305,"name":"Base Environment","parentId":"wrk_203fd2742f574ba3b18054d158f5d06f","_type":"environment"},{"_id":"jar_95be4cb6dfbce88b8b250b7576671f1b8111e4be","cookies":[],"created":1591628891978,"modified":1591628891978,"name":"Default Jar","parentId":"wrk_203fd2742f574ba3b18054d158f5d06f","_type":"cookie_jar"}]}